{
  "unversionedId": "tutorials/mathematics",
  "id": "tutorials/mathematics",
  "title": "Mathematics",
  "description": "Probability and Statistics",
  "source": "@site/docs/tutorials/mathematics.mdx",
  "sourceDirName": "tutorials",
  "slug": "/tutorials/mathematics",
  "permalink": "/recohut/docs/tutorials/mathematics",
  "editUrl": "https://github.com/sparsh-ai/recohut/docs/tutorials/mathematics.mdx",
  "tags": [],
  "version": "current",
  "frontMatter": {},
  "sidebar": "tutorialSidebar",
  "previous": {
    "title": "Graph-based Modeling",
    "permalink": "/recohut/docs/tutorials/graph"
  },
  "next": {
    "title": "Matrix Factorizations",
    "permalink": "/recohut/docs/tutorials/matrix-factorizations"
  }
}