{
  "unversionedId": "models/gce-gnn",
  "id": "models/gce-gnn",
  "title": "GCE-GNN",
  "description": "GCE-GNN stands for Global Context Enhanced Graph Neural Networks. It exploit item transitions over all sessions in a more subtle manner for better inferring the user preference of the current session.",
  "source": "@site/docs/models/gce-gnn.md",
  "sourceDirName": "models",
  "slug": "/models/gce-gnn",
  "permalink": "/recohut/docs/models/gce-gnn",
  "editUrl": "https://github.com/sparsh-ai/recohut/docs/models/gce-gnn.md",
  "tags": [],
  "version": "current",
  "frontMatter": {},
  "sidebar": "tutorialSidebar",
  "previous": {
    "title": "GC-SAN",
    "permalink": "/recohut/docs/models/gc-san"
  },
  "next": {
    "title": "GLMix",
    "permalink": "/recohut/docs/models/glmix"
  }
}